Metadata-Version: 2.1
Name: evmchain-etl-table-definition-cli
Version: 1.2.0
Summary: Tools for generating table definitions for https://github.com/blockchain-etl/ethereum-etl-airflow
Home-page: https://github.com/blockchain-etl/evmchain-etl-table-definition-cli
Author: Evgeny Medvedev
Author-email: evge.medvedev@gmail.com
License: UNKNOWN
Project-URL: Bug Reports, https://github.com/blockchain-etl/evmchain-etl-table-definition-cli/issues
Project-URL: Chat, https://gitter.im/ethereum-etl/Lobby
Project-URL: Source, https://github.com/blockchain-etl/evmchain-etl-table-definition-cli
Keywords: ethereum,polygon,bsc,arbitrum,fantom,celo,ronin,avalanche
Platform: UNKNOWN
Classifier: Development Status :: 5 - Production/Stable
Classifier: Intended Audience :: Developers
Classifier: License :: OSI Approved :: MIT License
Classifier: Programming Language :: Python :: 3
Classifier: Programming Language :: Python :: 3.5
Classifier: Programming Language :: Python :: 3.6
Classifier: Programming Language :: Python :: 3.7
Classifier: Programming Language :: Python :: 3.8
Requires-Python: >=3.5.3,<4
License-File: LICENSE
